{
    "id": "Outskirts - 07:41:13",
    "title": "Scrapland savegame",
    "data": {
        "CTFFinishPlayerLoosesTextCad": "Mission_CTFAgainstBankers_RemoteMessage3",
        "CTFFinishPlayerWinsTextCad": "Mission_CTFAgainstBankers_RemoteMessage2",
        "CTFStartTextCad": "Mission_CTFAgainstBankers_RemoteMessage1",
        "CTFOnDeathSpawnTime": "5.0",
        "CTFFriendProfile": "BankersCTFFriends",
        "CTFEnemyProfile": "BankersCTFEnemies",
        "CTFFriendHead": "Functionary",
        "CTFFriendType": "Functionary",
        "CTFEnemyType": "BankDirector",
        "CTFNumFriends": "5",
        "CTFNumEnemies": "5",
        "CTFFlags": "5",
        "CombatFriendProfile": "ArrangeBankersCombatFriends",
        "CombatFriendType": "Police",
        "CombatNumFriends": "4",
        "CombatNumEnemies": "5",
        "PlayerWinsCombat": "1",
        "OnVictory": "import SaveGame; SaveGame.QWayPoint();import MissionsFuncs; MissionsFuncs.SetNextMission(\"Mission_BackFromMortalRace\", \"GamblinDen\");Scrap.SetSaveVar(\"Map\", \"Levels/GamblinDen\");import SaveGame; SaveGame.QLoad(\"Levels/GamblinDen\");Scrap.SetSaveVar('MapPress_BureauExists','1')",
        "OnAbort": "import MissionsFuncs; MissionsFuncs.EndOfSuperDeal('SuperDeal_Faliure_SystemMessage1')",
        "CombatFinishPlayerLoosesTextCad": "SuperDeal_First_RemoteMessage3",
        "CombatFinishPlayerWinsTextCad": "SuperDeal_First_RemoteMessage2",
        "CombatStartTextCad": "SuperDeal_First_RemoteMessage1",
        "CombatEnemyProfile": "SuperDealFirstElite",
        "CombatEnemyTypeHead": "CrazyGambler",
        "CombatEnemyType": "BankDirector",
        "CombatDeaths": "5",
        "SuperDealType": "",
        "IgorFirstContactMissionState": "TalkToMercenaries",
        "Stats.MadHunter": "10",
        "Stats.Nurse.Dazed": "2",
        "Stats.BankMaster": "6758",
        "Bank.Circuit.36": "0",
        "Bank.Circuit.35": "0",
        "Bank.Circuit.34": "0",
        "Bank.Circuit.33": "0",
        "Bank.Circuit.32": "0",
        "Bank.Circuit.31": "0",
        "Bank.Circuit.30": "0",
        "Bank.Circuit.29": "0",
        "Bank.Circuit.28": "0",
        "Bank.Circuit.27": "0",
        "Bank.Circuit.26": "0",
        "Bank.Circuit.25": "0",
        "Bank.Circuit.24": "0",
        "Bank.Circuit.23": "0",
        "Bank.Circuit.22": "0",
        "Bank.Circuit.21": "0",
        "Bank.Circuit.20": "0",
        "Bank.Circuit.19": "0",
        "Bank.Circuit.18": "0",
        "Bank.Circuit.17": "0",
        "Bank.Circuit.16": "0",
        "Bank.Circuit.15": "0",
        "Bank.Circuit.14": "0",
        "Bank.Circuit.13": "0",
        "Bank.Circuit.12": "0",
        "Bank.Circuit.11": "0",
        "Bank.Circuit.10": "0",
        "Bank.Circuit.9": "0",
        "Bank.Circuit.8": "0",
        "Bank.Circuit.7": "0",
        "Bank.Circuit.6": "0",
        "Bank.Circuit.5": "0",
        "Bank.Circuit.4": "0",
        "Bank.Circuit.3": "0",
        "Bank.Circuit.2": "0",
        "Bank.Circuit.1": "0",
        "Bank.Circuit.0": "0",
        "Stats.Mosquito": "116",
        "PoliceBossAtTownHall": "0",
        "Stats.Parking": "18",
        "Police.FicusDeath": "1",
        "CostumeAtPolice": "0",
        "Hangar.HangarShip10": "SLifeBoat<-<-<-<-<-0,0,0,0,0,0,1<-30<-0,0,0,0,0,0",
        "Hangar.iHangarShips": "8",
        "AutoSaveGameOnLoad": "0",
        "GameAct": "3rdMurder",
        "BankDebt": "0",
        "Map": "Levels/Outskirts",
        "Mission.Library": "Mission_DestroyBadDebtors",
        "EnergyBarActive": "1",
        "SpecialActionActive": "2",
        "CrazyWing.Status": "1",
        "Conversor.ActiveConversors": "1",
        "Hangar.iHangarShip": "0",
        "Player.NumLives": "100",
        "Hangar.shipsToEditList": "['SPoli1', 'SPoli2', 'SPoli3', 'SPoli4', 'SPoli5', 'SPoliBoss1', 'SMerc1', 'SMerc2', 'SMerc3', 'SMayor1', 'SBanker1', 'SBankMaster1', 'SBishop1', 'SArchbishop1', 'SFunc1', 'SBerto1', 'SBetty1', 'SHump1', 'SBoss1', 'SPoli4']",
        "Hangar.availableEnginesList": "['MPOLI4', 'MPOLI5', 'MPOLIBOSS1', 'MPOLI2', 'MBERTO1', 'MBETTY1', 'MPOLI1', 'MMERC1', 'MMERC2', 'MPOLI3', 'MMAYOR1', 'MFUNC1', 'MBANKER1', 'MBANKMASTER1', 'MBISHOP1', 'MARCHBISHOP1', 'MHUMP1', 'MBOSS1', 'MMERC3']",
        "Hangar.availableWeaponsList": "['Vulcan', 'Devastator', 'Swarm', 'Inferno', 'Tesla', 'ATPC', 'Swarm', 'Devastator']",
        "Hangar.availableUpgradesList": "[\"VulcanUpgrade1\", \"VulcanUpgrade2\", \"DevastatorUpgrade1\", \"DevastatorUpgrade2\", \"SwarmUpgrade1\", \"SwarmUpgrade2\", \"InfernoUpgrade1\", \"InfernoUpgrade2\", \"TeslaUpgrade1\", \"TeslaUpgrade2\", \"ATPCUpgrade1\", \"ATPCUpgrade2\"]",
        "JackInTheBox.Active": "1",
        "Parked.Police": "['SPOLI1', 'SPOLI2', 'SPOLI3', 'SPOLI4']",
        "Parked.Mercs": "['SMERC1', 'SMERC2']",
        "Parked.TownHall": "['SFUNC1']",
        "Parked.Bank": "['SBANKER1']",
        "Parked.Press": "['SBERTO1', 'SBETTY1', 'SHUMP1']",
        "Parked.Temple": "['SBISHOP1']",
        "PoliceBlueprints.Ships": "['SPoli2', 'SPoli3', 'SPoli5', 'SPoliBoss1']",
        "PoliceBlueprints.Engines": "['MPoli2', 'MPoli3', 'MPoli4', 'MPoli5', 'MPoliBoss1']",
        "PressBlueprints.Ships": "['SBerto1', 'SBetty1', 'SHump1']",
        "PressBlueprints.Engines": "['MBerto1', 'MBetty1', 'MHump1']",
        "MayorAtGambinDen": "0",
        "PolicesAtGambinDen": "1",
        "PoliceBossAtPolice": "0",
        "CrazyGamblerAtGambinDen": "1",
        "FunctionaryTwinsAtGambinDen": "1",
        "BankersAtGambinDen": "0",
        "BishopsAtGambinDen": "0",
        "GameSkill": "0",
        "CreateBertos": "0",
        "MercsHelpDtritus": "0",
        "RobotsControlledByBoss": "0",
        "Player.InfiniteLives": "0",
        "PrevMap": "Levels/GamblinDen",
        "Spawn": "DM_Player_Spawn_GamblinDen",
        "Char": "Dtritus",
        "ComeFrom": "DoorElevator",
        "AlarmActive": "0",
        "AlarmStatus": "0.0",
        "Money": "2147483647",
        "Challenge": "1",
        "Challenge.Type": "",
        "Challenge.Foe": "",
        "Challenge.NumEnemies": "",
        "Challenge.Money": "0",
        "Revenge.Type": "",
        "Revenge.Foe": "",
        "Revenge.NumEnemies": "",
        "Revenge.LastWinner": "",
        "Mission.Map": "Outskirts",
        "BadReputation": "3",
        "GameplayTime": "27673.5857997",
        "LonelyMercInGamblinDen": "0",
        "LonelyMercLairActive": "1",
        "LonelyMercDataActive": "0",
        "ComSatsMissionsMapsFinished": "[]",
        "Conversor.AvailableChars": "['Police', 'Nurse', 'BankDirector', 'Desktop', 'Sentinel', 'Gear', 'Bishop', 'Messenger', 'Functionary', 'Betty', 'Berto', 'BankMaster', 'Dtritus']",
        "Batteries": "5",
        "AcBatteries": "2",
        "PrimaryMissionDesc": "Ich muss den Bankdirektor besuchen. Er treibt gerade ausstehende Kreditzahlungen mit seinem Kampfraumschiff ein. Ich sehe mal, ob ich ihm helfen kann.",
        "SecondaryMissionDesc": "",
        "TakePhotoMsg": "0",
        "Race.Num": "3",
        "Race.FirstTime": "0",
        "Race.Profile": "Pilot",
        "Combat.FirstTime": "1",
        "Combat.Profile": "Rookie",
        "Traffic.AcShips": "[\"SPoli6\", \"SMerc1\",\"SMerc2\",\"SBanker1\"]",
        "IsSecondMission": "0",
        "CrazyDeal.1.Var": "Stats.Dtritus",
        "CrazyDeal.1.Tgt": "5",
        "CrazyDeal.2.Var": "Stats.Parking",
        "CrazyDeal.2.Tgt": "3",
        "CrazyDeal.3.Var": "Stats.Battery",
        "CrazyDeal.3.Tgt": "5",
        "SuperDeal.Map": "FZ",
        "SuperDeal.Library": "SuperDeal_Second",
        "SuperDeal.Type": "MortalRace",
        "CrazyWing.List": "['Sentinel', 'Betty', 'CrazyGambler', 'Functionary', 'Bishop']",
        "Journalist.Humphrey_Defaut": "NoPlace",
        "Journalist.Betty_Defaut": "NoPlace",
        "Journalist.Berto_Defaut": "Press",
        "Conversor.FirstConversion": "0",
        "Conversor.FirstPossession": "0",
        "WindowsError": "0",
        "Orbit.Decontaminated": "yes",
        "MercFriends.MercenaryA_Smartie": "0",
        "MercFriends.MercenaryC_Brutus": "0",
        "MercFriends.MercenaryB_Dumber": "0",
        "StdShipAIProfile": "Elite",
        "usrShip.Ammo00": "1000.0",
        "usrShip.Ammo01": "500.0",
        "usrShip.Ammo02": "1500.0",
        "usrShip.AcWeap": "6",
        "Parking.Desolate": "0",
        "Hangar.HangarShip1": "SBoss1<-MBOSS1<-MBOSS1<-<-<-15,15,15,15,15,15,1<-187<-1,8,6,9,11,3",
        "Hangar.HangarShip2": "",
        "Hangar.HangarShip3": "",
        "Hangar.HangarShip4": "",
        "Hangar.HangarShip5": "",
        "Hangar.HangarShip6": "",
        "Hangar.HangarShip7": "",
        "Hangar.HangarShip8": "",
        "Hangar.HangarShip9": "",
        "Hangar.HangarShipAux": "SLifeBoat<-<-<-<-<-0,0,0,0,0,0,1<-50<-0,0,0,0,0,0",
        "Hangar.DestroyedShips": "[0, 0, 0, 0, 0, 0, 0, 0, 0, 0]",
        "NewBluePrintAvaliable": "11",
        "DebugSave": "1",
        "OutMusicRelax": "141",
        "MayorAtTownHall": "1",
        "GamblinMusic": "1",
        "OutMusicAction": "122",
        "Stats.Traffic": "767",
        "Stats.OutPolice": "110",
        "MapPress_HiAlarm": "0",
        "MapPress_BureauExists": "1",
        "Stats.PossessBerto": "1",
        "Stats.ConvertIntoDtritus": "1",
        "Stats.WinHumphreyRace": "1",
        "Stats.Possession": "57",
        "Stats.Betty": "49",
        "Stats.Killer": "119",
        "Stats.Jump": "1",
        "Stats.Jump.Police": "1",
        "Stats.Bishop": "10",
        "Stats.Battery": "0",
        "Stats.Dtritus": "0",
        "Stats.Race.Press": "1",
        "Stats.TotalRaces.Press": "1",
        "BankMasterAtBank": "1",
        "DM_ExtraLife_00": "-60",
        "DM_ExtraLife_01": "-60",
        "DM_ExtraLife_02": "-60",
        "DM_ExtraLife_03": "-60",
        "DM_ExtraLife_04": "16294.7919922",
        "Stats.TempleLife": "4",
        "Mission_CatchTrurl_Data": "[]",
        "Mission_CatchTrurl_MapsPos": "[]",
        "Mission_CatchTrurl_NumMapsDropped": "0",
        "Mission_CatchTrurl_NumMapsTaken": "0",
        "GDB.BishopsMsg": "1",
        "Stats.GDB": "6",
        "LonelyMercActive": "0",
        "Stats.Messenger": "2",
        "MortalRaceRace": "[((71611.59375, 18231.6992188, 93232.796875), 422.337219238), ((45388.4140625, 14599.3476563, 79622.6640625), 400.984222412), ((25194.9804688, 18783.4863281, 59759.296875), 404.390136719), ((-433.664245605, 26340.1289063, 34561.0898438), 409.718261719), ((-38229.3671875, 26457.5292969, 679.068054199), 449.472442627), ((-107464.132813, 19331.875, 3288.328125), 528.452758789), ((-113911.117188, 14331.4462891, 40812.9414063), 558.054199219), ((-102532.132813, 11236.1474609, 75072.375), 630.567077637), ((-58177.6289063, 6282.20654297, 74209.3515625), 673.615478516), ((-24157.5449219, 7054.30419922, 43223.1679688), 630.510681152), ((33550.1445313, 15480.2402344, 41122.5820313), -55.4565696716), ((56201.6054688, 15587.5126953, 24649.8496094), 23.7488441467), ((26343.9511719, 22077.8789063, -32317.0292969), 90.5086135864), ((-13835.4755859, 26276.8730469, -31975.1582031), 145.932754517), ((-29244.3652344, 26745.4667969, -2544.81738281), -892.995666504), ((-23808.9570313, 27246.9980469, 32018.1816406), -819.383483887), ((21584.3066406, 29452.4667969, 41221.6171875), -822.313781738), ((54026.796875, 24611.7421875, 42694.0898438), -802.188171387), ((95732.015625, 16516.8085938, 36323.546875), -872.699890137), ((113450.46875, 12325.5195313, 77796.75), -969.003662109)]",
        "MortalRaceWaypoints": "20",
        "MortalRaceRacers": "['ArchBishop', 'BankDirector', 'Functionary', 'MercenaryA', 'MercenaryB']",
        "MortalRaceRacersProfile": "MortalRace",
        "MortalRaceFightingFreezeControlAim": "4",
        "MortalRaceRespawnTime": "5.0",
        "MortalRaceStartTextCad": "Mission_WinMortalRace_RemoteMessage1",
        "MortalRaceFinishPlayerLoosesTextCad": "Mission_WinMortalRace_RemoteMessage2",
        "MortalRaceFinishPlayerLoosesTextFoe": "Messenger",
        "MortalRaceFinishPlayerWinsTextCad": "Mission_WinMortalRace_RemoteMessage3",
        "MortalRaceFinishPlayerWinsTextFoe": "Messenger",
        "MortalRaceAutoRestart": "1"
    }
}